cat/experiments/__init__.py
cat/experiments/_version.py
cat/experiments/executor/__init__.py
cat/experiments/executor/executor.py
cat/experiments/executor/executor_main.py
cat/experiments/executor/executor_pipe.py
cat/experiments/protocol/__init__.py
cat/experiments/protocol/serde.py
cat/experiments/protocol/types.py
cat/experiments/sdk/__init__.py
cat/experiments/sdk/agg_ci.py
cat/experiments/sdk/decorators.py
cat/experiments/sdk/tools.py
cat/experiments/sdk/tracing/__init__.py
cat/experiments/sdk/tracing/_otel.py
cat/experiments/sdk/tracing/extractors.py
cat_experiments-0.0.12.data/scripts/cat-experiments
cat_experiments-0.0.12.dist-info/METADATA
cat_experiments-0.0.12.dist-info/WHEEL
cat_experiments-0.0.12.dist-info/entry_points.txt
cat_experiments-0.0.12.dist-info/licenses/LICENSE
cat_experiments-0.0.12.dist-info/RECORD
