Metadata-Version: 2.4
Name: cat-experiments
Version: 0.0.12
Summary: Standalone evaluation engine for LLM applications
Author-email: CAT Cafe Team <team@cat-cafe.dev>
License: Apache-2.0
License-File: LICENSE
Keywords: ai,evaluation,llm,testing
Classifier: Development Status :: 3 - Alpha
Classifier: Intended Audience :: Developers
Classifier: License :: OSI Approved :: Apache Software License
Classifier: Programming Language :: Python :: 3
Classifier: Programming Language :: Python :: 3.12
Classifier: Topic :: Scientific/Engineering :: Artificial Intelligence
Classifier: Topic :: Software Development :: Testing
Requires-Python: >=3.12
Requires-Dist: typing-extensions>=4.5.0
Provides-Extra: cat-cafe
Requires-Dist: cat-cafe-client>=0.0.3; extra == 'cat-cafe'
Provides-Extra: phoenix
Requires-Dist: arize-phoenix-client>=1.22.0; extra == 'phoenix'
Provides-Extra: tracing
Requires-Dist: opentelemetry-api>=1.36.0; extra == 'tracing'
Requires-Dist: opentelemetry-sdk>=1.36.0; extra == 'tracing'
